phrase_tokenizer/__init__.py
phrase_tokenizer/phrase_tok.py
phrase_tokenizer-0.1.3.dist-info/LICENSE
phrase_tokenizer-0.1.3.dist-info/WHEEL
phrase_tokenizer-0.1.3.dist-info/METADATA
phrase_tokenizer-0.1.3.dist-info/RECORD
