Metadata-Version: 2.1
Name: phrase-tokenizer
Version: 0.1.3
Summary: Tokenize an English sentence to phrases
Home-page: https://github.com/ffreemt/phrase-tokenizer
Author: ffreemt
Requires-Python: >=3.7,<4.0
Classifier: Programming Language :: Python :: 3
Classifier: Programming Language :: Python :: 3.10
Classifier: Programming Language :: Python :: 3.7
Classifier: Programming Language :: Python :: 3.8
Classifier: Programming Language :: Python :: 3.9
Requires-Dist: benepar (>=0.2.0,<0.3.0)
Requires-Dist: logzero (>=1.6.3,<2.0.0)
Requires-Dist: nltk (>=3.2.5,<4.0.0)
Requires-Dist: svgling (>=0.3.0,<0.4.0)
Project-URL: Bug Tracker, https://github.com/ffreemt/phrase-tokenizer/issues
Project-URL: Repository, https://github.com/ffreemt/phrase-tokenizer
